nanonets_docparser-0.1.0.dist-info/licenses/LICENSE
nanonets_extractor/__init__.py
nanonets_extractor/cli.py
nanonets_extractor/exceptions.py
nanonets_extractor/extractor.py
nanonets_extractor/utils.py
nanonets_extractor/processors/__init__.py
nanonets_extractor/processors/base_processor.py
nanonets_extractor/processors/cloud_processor.py
nanonets_extractor/processors/cpu_processor.py
nanonets_extractor/processors/gpu_processor.py
nanonets_docparser-0.1.0.dist-info/METADATA
nanonets_docparser-0.1.0.dist-info/WHEEL
nanonets_docparser-0.1.0.dist-info/entry_points.txt
nanonets_docparser-0.1.0.dist-info/top_level.txt
nanonets_docparser-0.1.0.dist-info/RECORD
