Metadata-Version: 2.4
Name: nanonets-docparser
Version: 0.1.0
Summary: A unified document extraction library supporting local CPU, GPU, and cloud processing
Home-page: https://github.com/nanonets/document-extractor
Author: Nanonets
Author-email: Nanonets <support@nanonets.com>
Maintainer-email: Nanonets <support@nanonets.com>
License: MIT
Project-URL: Homepage, https://github.com/nanonets/document-extractor
Project-URL: Documentation, https://docs.nanonets.com
Project-URL: Repository, https://github.com/nanonets/document-extractor
Project-URL: Bug Tracker, https://github.com/nanonets/document-extractor/issues
Project-URL: API Keys, https://app.nanonets.com/#/keys
Keywords: document,extraction,ocr,pdf,ai,machine-learning
Classifier: Development Status :: 4 - Beta
Classifier: Intended Audience :: Developers
Classifier: License :: OSI Approved :: MIT License
Classifier: Operating System :: OS Independent
Classifier: Programming Language :: Python :: 3
Classifier: Programming Language :: Python :: 3.8
Classifier: Programming Language :: Python :: 3.9
Classifier: Programming Language :: Python :: 3.10
Classifier: Programming Language :: Python :: 3.11
Classifier: Programming Language :: Python :: 3.12
Classifier: Topic :: Scientific/Engineering :: Artificial Intelligence
Classifier: Topic :: Software Development :: Libraries :: Python Modules
Classifier: Topic :: Text Processing :: General
Requires-Python: >=3.8
License-File: LICENSE
Requires-Dist: requests>=2.25.0
Requires-Dist: Pillow>=8.0.0
Requires-Dist: PyPDF2>=2.0.0
Requires-Dist: python-docx>=0.8.11
Requires-Dist: openpyxl>=3.0.0
Requires-Dist: pandas>=1.3.0
Requires-Dist: numpy>=1.21.0
Requires-Dist: opencv-python>=4.5.0
Requires-Dist: pytesseract>=0.3.8
Requires-Dist: transformers>=4.20.0
Requires-Dist: torch>=1.12.0
Requires-Dist: torchvision>=0.13.0
Requires-Dist: easyocr>=1.6.0
Requires-Dist: pydantic>=1.9.0
Requires-Dist: typing-extensions>=4.0.0
Provides-Extra: gpu
Requires-Dist: torch>=1.12.0; extra == "gpu"
Requires-Dist: torchvision>=0.13.0; extra == "gpu"
Provides-Extra: dev
Requires-Dist: pytest>=6.0.0; extra == "dev"
Requires-Dist: pytest-cov>=2.10.0; extra == "dev"
Requires-Dist: black>=21.0.0; extra == "dev"
Requires-Dist: flake8>=3.8.0; extra == "dev"
Requires-Dist: mypy>=0.910; extra == "dev"
Dynamic: author
Dynamic: home-page
Dynamic: license-file
Dynamic: requires-python
